<?xml version="1.0" encoding="UTF-8" standalone="yes"?>
<customer>
    <customer>
        <city>Nottingham</city>
        <emailAddress>jonas.schindler@gmail.com</emailAddress>
        <firstName>Jonas</firstName>
        <lastName>Schindler</lastName>
        <password>password</password>
        <street>1 Peveril Street</street>
    </customer>
    <customer>
        <city></city>
        <emailAddress></emailAddress>
        <firstName>Martin</firstName>
        <lastName></lastName>
        <password>12345</password>
        <street></street>
    </customer>
    <customer>
        <city></city>
        <emailAddress></emailAddress>
        <firstName>bill</firstName>
        <lastName></lastName>
        <password>password</password>
        <street></street>
    </customer>
    <customer>
        <city></city>
        <emailAddress></emailAddress>
        <firstName>martin</firstName>
        <lastName></lastName>
        <password>0000</password>
        <street></street>
    </customer>
</customer>
